virtualenvconfig.py
virtualenvconfig-0.0.8.dist-info/LICENSE
virtualenvconfig-0.0.8.dist-info/METADATA
virtualenvconfig-0.0.8.dist-info/WHEEL
virtualenvconfig-0.0.8.dist-info/top_level.txt
virtualenvconfig-0.0.8.dist-info/RECORD
