Metadata-Version: 2.1
Name: virtualenvconfig
Version: 0.0.8
Summary: Customize abi resolution for a given virtualenv setup.
Home-page: https://github.com/blurstudio/virtualenvconfig
Author: Blur Studio
Author-email: pipeline@blur.com
License: GNU LGPLv3
Download-URL: https://github.com/blurstudio/virtualenvconfig/archive/master.zip
Platform: UNKNOWN
Classifier: Development Status :: 3 - Alpha
Classifier: Intended Audience :: Developers
Classifier: Programming Language :: Python
Classifier: Programming Language :: Python :: 2
Classifier: Programming Language :: Python :: 2.7
Classifier: Programming Language :: Python :: Implementation :: CPython
Classifier: Programming Language :: Python :: Implementation :: PyPy
Classifier: Operating System :: OS Independent
Classifier: License :: OSI Approved :: GNU Lesser General Public License v3 (LGPLv3)
Requires-Dist: gorilla
Requires-Dist: pip (>=19.1.1)
